[{"filename": "Screenshot 2026-03-31 165421.png", "location": "library", "contact": "1234t", "description": "water bottel", "category": "Others"}, {"filename": "1777791657_test.png", "location": "loc_0", "contact": "123", "description": "item 0", "category": "Others"}, {"filename": "1777791657_test.png", "location": "loc_1", "contact": "123", "description": "item 1", "category": "Others"}, {"filename": "1777791658_test.png", "location": "loc_2", "contact": "123", "description": "item 2", "category": "Others"}]